mathpyt/1.py
mathpyt/__init__.py
mathpyt/calculus.py
mathpyt/combinatorics.py
mathpyt/complex_analysis.py
mathpyt/cryptography.py
mathpyt/differential_equations.py
mathpyt/geometry.py
mathpyt/graph_theory.py
mathpyt/linear_algebra.py
mathpyt/number_theory.py
mathpyt/numerical_methods.py
mathpyt/optimization.py
mathpyt/probability.py
mathpyt/statistics.py
mathpyt-0.1.0.dist-info/licenses/LICENSE
mathpyt-0.1.0.dist-info/METADATA
mathpyt-0.1.0.dist-info/WHEEL
mathpyt-0.1.0.dist-info/top_level.txt
mathpyt-0.1.0.dist-info/RECORD
